.gitignore
.travis.yml
CHANGES.rst
LICENSE
MANIFEST.in
Makefile
README.rst
load_tester.py
queuey.spec
requirements.txt
runtests.py
setup.py
start.sh
docs/Makefile
docs/api.rst
docs/changelog.rst
docs/conf.py
docs/configuration.rst
docs/index.rst
docs/installation.rst
docs/make.bat
etc/production.ini
etc/queuey-dev.ini
etc/queuey-test.ini
etc/queuey.nginx.conf
etc/supervisord.conf
etc/cassandra/cassandra-cluster-template.yaml
etc/cassandra/cassandra.yaml
etc/cassandra/log4j-server.properties
queuey/__init__.py
queuey/exceptions.py
queuey/resources.py
queuey/run.py
queuey/security.py
queuey/testing.py
queuey/validators.py
queuey/views.py
queuey.egg-info/PKG-INFO
queuey.egg-info/SOURCES.txt
queuey.egg-info/dependency_links.txt
queuey.egg-info/entry_points.txt
queuey.egg-info/not-zip-safe
queuey.egg-info/requires.txt
queuey.egg-info/top_level.txt
queuey/storage/__init__.py
queuey/storage/cassandra.py
queuey/storage/memory.py
queuey/storage/util.py
queuey/tests/__init__.py
queuey/tests/storage.py
queuey/tests/test_cassandra.ini
queuey/tests/test_cassandra.py
queuey/tests/test_integrated.py
queuey/tests/test_memory.ini
queuey/tests/test_memory.py
sw/virtualenv.py
var/README.txt