Metadata-Version: 1.1
Name: queuey
Version: 0.8
Summary: RESTful Message Queue
Home-page: http://queuey.readthedocs.org/
Author: Mozilla Foundation
Author-email: bbangert@mozilla.com
License: MPLv2.0
Keywords: message-queue notifications server messaging queue
Platform: UNKNOWN
Classifier: Intended Audience :: Developers
Classifier: Programming Language :: Python
Classifier: License :: OSI Approved :: Mozilla Public License 2.0 (MPL 2.0)
Classifier: Programming Language :: Python
Classifier: Programming Language :: Python :: 2.6
Classifier: Programming Language :: Python :: 2.7
